mei_yong/__init__.py
mei_yong/cli.py
mei_yong-1.0.0.dist-info/METADATA
mei_yong-1.0.0.dist-info/WHEEL
mei_yong-1.0.0.dist-info/entry_points.txt
mei_yong-1.0.0.dist-info/top_level.txt
mei_yong-1.0.0.dist-info/RECORD
